{
  "Initialization": {
    "BatchSize": 5000,
    "BatchSleepSeconds": 10
  },

  "GalleryDb": {
    "ConnectionString": "Data Source=tcp:#{Deployment.Azure.Sql.GalleryDatabaseAddress};Initial Catalog=nuget-int-0-v2gallery;User ID=$$Int-GalleryDBWriter-UserName$$;Password=$$Int-GalleryDBWriter-Password$$;Encrypt=True;TrustServerCertificate=False;Connection Timeout=30;"
  },

  "StatisticsDb": {
    "ConnectionString": "Data Source=tcp:#{Deployment.Azure.Sql.StatisticsDatabaseAddress};Initial Catalog=nuget-int-statistics;User ID=$$Int-StatisticsDBWriter-UserName$$;Password=$$Int-StatisticsDBWriter-Password$$;Encrypt=True;TrustServerCertificate=False;Connection Timeout=30;"
  },

  "KeyVault_VaultName": "#{Deployment.Azure.KeyVault.VaultName}",
  "KeyVault_ClientId": "#{Deployment.Azure.KeyVault.ClientId}",
  "KeyVault_CertificateThumbprint": "#{Deployment.Azure.KeyVault.CertificateThumbprint}",
  "KeyVault_ValidateCertificate": true,
  "KeyVault_StoreName": "My",
  "KeyVault_StoreLocation": "LocalMachine"
}